[
    {
        "key": "cleared",
        "color": "#439666",
        "label": {
            "fr": "Déneigé",
            "en": "Cleared"
        }
    },
    {
        "key": "partially-cleared",
        "color": "#367c99",
        "label": {
            "fr": "Un côté déneigé",
            "en": "One side cleared"
        }
    },
    {
        "key": "snowy",
        "color": "#f09035",
        "label": {
            "fr": "Enneigé",
            "en": "Snowy"
        }
    },
    {
        "key": "planified",
        "color": "#83b5e0",
        "label": {
            "fr": "Déneigement planifié",
            "en": "Clearing planned"
        }
    },
    {
        "key": "clearing",
        "color": "#ff0000",
        "label": {
            "fr": "Déneigement en cours",
            "en": "Clearing in progress"
        }
    },
    {
        "key": "unknown",
        "color": "#666666",
        "label": {
            "fr": "Non planifié",
            "en": "Not planned"
        }
    }
]